pyfr/__init__.py
pyfr/__main__.py
pyfr/_version.py
pyfr/ctypesutil.py
pyfr/inifile.py
pyfr/mpiutil.py
pyfr/nputil.py
pyfr/polys.py
pyfr/progress.py
pyfr/rank_allocator.py
pyfr/regions.py
pyfr/shapes.py
pyfr/template.py
pyfr/util.py
pyfr/backends/__init__.py
pyfr/backends/base/__init__.py
pyfr/backends/base/backend.py
pyfr/backends/base/generator.py
pyfr/backends/base/kernels.py
pyfr/backends/base/makoutil.py
pyfr/backends/base/types.py
pyfr/backends/cuda/__init__.py
pyfr/backends/cuda/base.py
pyfr/backends/cuda/blasext.py
pyfr/backends/cuda/compiler.py
pyfr/backends/cuda/cublaslt.py
pyfr/backends/cuda/driver.py
pyfr/backends/cuda/generator.py
pyfr/backends/cuda/gimmik.py
pyfr/backends/cuda/packing.py
pyfr/backends/cuda/provider.py
pyfr/backends/cuda/types.py
pyfr/backends/cuda/kernels/__init__.py
pyfr/backends/cuda/kernels/axnpby.mako
pyfr/backends/cuda/kernels/base.mako
pyfr/backends/cuda/kernels/pack.mako
pyfr/backends/cuda/kernels/reduction.mako
pyfr/backends/hip/__init__.py
pyfr/backends/hip/base.py
pyfr/backends/hip/blasext.py
pyfr/backends/hip/compiler.py
pyfr/backends/hip/driver.py
pyfr/backends/hip/generator.py
pyfr/backends/hip/gimmik.py
pyfr/backends/hip/packing.py
pyfr/backends/hip/provider.py
pyfr/backends/hip/rocblas.py
pyfr/backends/hip/types.py
pyfr/backends/hip/kernels/__init__.py
pyfr/backends/hip/kernels/axnpby.mako
pyfr/backends/hip/kernels/base.mako
pyfr/backends/hip/kernels/pack.mako
pyfr/backends/hip/kernels/reduction.mako
pyfr/backends/metal/__init__.py
pyfr/backends/metal/base.py
pyfr/backends/metal/blasext.py
pyfr/backends/metal/generator.py
pyfr/backends/metal/gimmik.py
pyfr/backends/metal/mps.py
pyfr/backends/metal/packing.py
pyfr/backends/metal/provider.py
pyfr/backends/metal/types.py
pyfr/backends/metal/util.py
pyfr/backends/metal/kernels/__init__.py
pyfr/backends/metal/kernels/axnpby.mako
pyfr/backends/metal/kernels/base.mako
pyfr/backends/metal/kernels/pack.mako
pyfr/backends/metal/kernels/reduction.mako
pyfr-2.1.dist-info/AUTHORS
pyfr-2.1.dist-info/LICENSE
pyfr-2.1.dist-info/METADATA
pyfr-2.1.dist-info/WHEEL
pyfr-2.1.dist-info/entry_points.txt
pyfr-2.1.dist-info/top_level.txt
pyfr-2.1.dist-info/RECORD
