Metadata-Version: 2.1
Name: pyfr
Version: 2.1
Summary: Flux Reconstruction in Python
Home-page: http://www.pyfr.org/
Author: Imperial College London
Author-email: info@pyfr.org
License: BSD
Keywords: Math
Classifier: License :: OSI Approved :: BSD License
Classifier: Programming Language :: Python
Classifier: Programming Language :: Python :: 3.10
Classifier: Topic :: Scientific/Engineering
Requires-Python: >=3.10
License-File: LICENSE
License-File: AUTHORS
Requires-Dist: gimmik >=3.2.1
Requires-Dist: h5py >=2.10
Requires-Dist: mako >=1.0.0
Requires-Dist: mpi4py >=3.1.0
Requires-Dist: numpy >=1.26.4
Requires-Dist: platformdirs >=2.2.0
Requires-Dist: pytools >=2016.2.1
Requires-Dist: rtree >=1.0.1
Provides-Extra: metal
Requires-Dist: pyobjc-framework-Metal >=9.0 ; extra == 'metal'
